fishbowl_detect-0.2.3.dist-info/METADATA
fishbowl_detect-0.2.3.dist-info/WHEEL
fishbowl/__init__.py
fishbowl/fishbowl.cpython-312-x86_64-linux-gnu.so
fishbowl_detect-0.2.3.dist-info/RECORD
