Metadata-Version: 2.1
Name: fishbowl-detect
Version: 0.2.3
Classifier: Programming Language :: Rust
Classifier: Programming Language :: Python :: Implementation :: CPython
Requires-Python: >=3.8
